README
main.py
setup.py
Learn_Tibetan.egg-info/PKG-INFO
Learn_Tibetan.egg-info/SOURCES.txt
Learn_Tibetan.egg-info/dependency_links.txt
Learn_Tibetan.egg-info/requires.txt
Learn_Tibetan.egg-info/top_level.txt