Metadata-Version: 1.1
Name: Learn-Tibetan
Version: 0.0.1.dev1
Summary: Quiz for learn tibetan
Home-page: https://budismoclasico.wordpress.com/tibetano/
Author: mUniKeS
Author-email: munikes@members.fsf.org
License: GPL v3
Download-URL: https://gitorious.org/tibetan_culture/learn_tibetan
Keywords: tibetan,quiz,learn
Platform: UNKNOWN
